{
    "AssertAllocation": [
        {
            "TransDate": "20160601",
            "Name": "股票",
            "InvRate": 0.8528475,
            "SInvRate": 85.28475,
            "LInvRate": 85.28475
        },
        {
            "TransDate": "20160601",
            "Name": "現金",
            "InvRate": 0.1471525,
            "SInvRate": 14.71525,
            "LInvRate": 14.71525
        }
    ],
    "IndustryRatio": [
        {
            "TransDate": "20160601",
            "Name": "Engineering & Construction",
            "InvRate": 16.49741
        },
        {
            "TransDate": "20160601",
            "Name": "Autos",
            "InvRate": 16.36622
        },
        {
            "TransDate": "20160601",
            "Name": "Aerospace & Defense",
            "InvRate": 11.7447
        },
        {
            "TransDate": "20160601",
            "Name": "Travel & Leisure",
            "InvRate": 9.14695
        },
        {
            "TransDate": "20160601",
            "Name": "Banks",
            "InvRate": 8.01237
        },
        {
            "TransDate": "20160601",
            "Name": "Oil & Gas - Refining & Marketing",
            "InvRate": 5.09453
        },
        {
            "TransDate": "20160601",
            "Name": "Retail - Apparel & Specialty",
            "InvRate": 4.42506
        },
        {
            "TransDate": "20160601",
            "Name": "Entertainment",
            "InvRate": 4.21161
        },
        {
            "TransDate": "20160601",
            "Name": "Manufacturing - Apparel & Furniture",
            "InvRate": 3.92356
        },
        {
            "TransDate": "20160601",
            "Name": "Medical Devices",
            "InvRate": 3.25764
        },
        {
            "TransDate": "20160601",
            "Name": "Semiconductors",
            "InvRate": 2.6047
        }
    ],
    "StockTop": [
        {
            "TransDate": "20160601",
            "ExternalName": "SHINHAN FINANCIAL GROUP CO LTD ORD KRW5000",
            "InvRate": 8.01235
        },
        {
            "TransDate": "20160601",
            "ExternalName": "DAELIM INDUSTRIAL CO ORD KRW5000",
            "InvRate": 7.83971
        },
        {
            "TransDate": "20160601",
            "ExternalName": "SAMSUNG HEAVY INDUSTRIES CO LTD ORD KRW5000",
            "InvRate": 7.72641
        },
        {
            "TransDate": "20160601",
            "ExternalName": "HYUNDAI DEVELOPMENT CO ORD KRW5000",
            "InvRate": 4.78182
        },
        {
            "TransDate": "20160601",
            "ExternalName": "YOUNGONE HOLDINGS CO LTD ORD KRW500",
            "InvRate": 4.69329
        },
        {
            "TransDate": "20160601",
            "ExternalName": "YOUNGONE CORP ORD KRW500",
            "InvRate": 4.45366
        },
        {
            "TransDate": "20160601",
            "ExternalName": "KIA MOTORS CORP ORD KRW5000",
            "InvRate": 4.32405
        },
        {
            "TransDate": "20160601",
            "ExternalName": "GS HOME SHOPPING INC ORD KRW5000",
            "InvRate": 4.21161
        },
        {
            "TransDate": "20160601",
            "ExternalName": "HANKOOK TIRE CO LTD ORD KRW500",
            "InvRate": 4.1036
        },
        {
            "TransDate": "20160601",
            "ExternalName": "KOLAO HOLDINGS ORD KRW.25",
            "InvRate": 4.08953
        }
    ]
}