[
    {
        "Currency": "USD",
        "TransDate": "20161108",
        "Div": 0.34
    },
    {
        "Currency": "USD",
        "TransDate": "20161012",
        "Div": 0.357
    },
    {
        "Currency": "USD",
        "TransDate": "20160912",
        "Div": 0.357
    },
    {
        "Currency": "USD",
        "TransDate": "20160809",
        "Div": 0.357
    },
    {
        "Currency": "USD",
        "TransDate": "20160708",
        "Div": 0.34
    },
    {
        "Currency": "USD",
        "TransDate": "20160608",
        "Div": 0.34
    },
    {
        "Currency": "USD",
        "TransDate": "20160510",
        "Div": 0.34
    },
    {
        "Currency": "USD",
        "TransDate": "20160408",
        "Div": 0.34
    },
    {
        "Currency": "USD",
        "TransDate": "20160308",
        "Div": 0.34
    },
    {
        "Currency": "USD",
        "TransDate": "20160212",
        "Div": 0.34
    },
    {
        "Currency": "USD",
        "TransDate": "20160108",
        "Div": 0.34
    },
    {
        "Currency": "USD",
        "TransDate": "20151208",
        "Div": 0.34
    },
    {
        "Currency": "USD",
        "TransDate": "20151110",
        "Div": 0.34
    },
    {
        "Currency": "USD",
        "TransDate": "20151008",
        "Div": 0.34
    },
    {
        "Currency": "USD",
        "TransDate": "20150909",
        "Div": 0.34
    },
    {
        "Currency": "USD",
        "TransDate": "20150810",
        "Div": 0.34
    },
    {
        "Currency": "USD",
        "TransDate": "20150708",
        "Div": 0.34
    },
    {
        "Currency": "USD",
        "TransDate": "20150609",
        "Div": 0.34
    },
    {
        "Currency": "USD",
        "TransDate": "20150508",
        "Div": 0.34
    },
    {
        "Currency": "USD",
        "TransDate": "20150408",
        "Div": 0.34
    },
    {
        "Currency": "USD",
        "TransDate": "20150310",
        "Div": 0.34
    },
    {
        "Currency": "USD",
        "TransDate": "20150210",
        "Div": 0.34
    },
    {
        "Currency": "USD",
        "TransDate": "20150108",
        "Div": 0.346
    },
    {
        "Currency": "USD",
        "TransDate": "20141209",
        "Div": 0.346
    },
    {
        "Currency": "USD",
        "TransDate": "20141110",
        "Div": 0.346
    }
]