[
    {
        "Currency": "ZAR",
        "TransDate": "20161130",
        "Div": 0.59
    },
    {
        "Currency": "ZAR",
        "TransDate": "20161031",
        "Div": 0.59
    },
    {
        "Currency": "ZAR",
        "TransDate": "20160930",
        "Div": 0.59
    },
    {
        "Currency": "ZAR",
        "TransDate": "20160831",
        "Div": 0.59
    },
    {
        "Currency": "ZAR",
        "TransDate": "20160729",
        "Div": 0.59
    },
    {
        "Currency": "ZAR",
        "TransDate": "20160630",
        "Div": 0.59
    },
    {
        "Currency": "ZAR",
        "TransDate": "20160531",
        "Div": 0.59
    },
    {
        "Currency": "ZAR",
        "TransDate": "20160429",
        "Div": 0.59
    },
    {
        "Currency": "ZAR",
        "TransDate": "20160331",
        "Div": 0.59
    },
    {
        "Currency": "ZAR",
        "TransDate": "20160229",
        "Div": 0.59
    },
    {
        "Currency": "ZAR",
        "TransDate": "20160129",
        "Div": 0.59
    },
    {
        "Currency": "ZAR",
        "TransDate": "20151231",
        "Div": 0.663
    },
    {
        "Currency": "ZAR",
        "TransDate": "20151130",
        "Div": 0.663
    },
    {
        "Currency": "ZAR",
        "TransDate": "20151030",
        "Div": 0.663
    },
    {
        "Currency": "ZAR",
        "TransDate": "20150930",
        "Div": 0.663
    },
    {
        "Currency": "ZAR",
        "TransDate": "20150831",
        "Div": 0.663
    },
    {
        "Currency": "ZAR",
        "TransDate": "20150731",
        "Div": 0.663
    },
    {
        "Currency": "ZAR",
        "TransDate": "20150630",
        "Div": 0.663
    },
    {
        "Currency": "ZAR",
        "TransDate": "20150529",
        "Div": 0.663
    },
    {
        "Currency": "ZAR",
        "TransDate": "20150430",
        "Div": 0.663
    },
    {
        "Currency": "ZAR",
        "TransDate": "20150331",
        "Div": 0.663
    },
    {
        "Currency": "ZAR",
        "TransDate": "20150227",
        "Div": 0.663
    },
    {
        "Currency": "ZAR",
        "TransDate": "20150130",
        "Div": 0.663
    },
    {
        "Currency": "ZAR",
        "TransDate": "20141231",
        "Div": 0.663
    },
    {
        "Currency": "ZAR",
        "TransDate": "20141128",
        "Div": 0.663
    },
    {
        "Currency": "ZAR",
        "TransDate": "20141031",
        "Div": 0.663
    }
]