[
    {
        "Currency": "EUR",
        "TransDate": "20161115",
        "Div": 0.47
    },
    {
        "Currency": "EUR",
        "TransDate": "20161017",
        "Div": 0.48
    },
    {
        "Currency": "EUR",
        "TransDate": "20160915",
        "Div": 0.48
    },
    {
        "Currency": "EUR",
        "TransDate": "20160816",
        "Div": 0.48
    },
    {
        "Currency": "EUR",
        "TransDate": "20160715",
        "Div": 0.47
    },
    {
        "Currency": "EUR",
        "TransDate": "20160615",
        "Div": 0.47
    },
    {
        "Currency": "EUR",
        "TransDate": "20160517",
        "Div": 0.47
    },
    {
        "Currency": "EUR",
        "TransDate": "20160415",
        "Div": 0.47
    },
    {
        "Currency": "EUR",
        "TransDate": "20160315",
        "Div": 0.46
    },
    {
        "Currency": "EUR",
        "TransDate": "20160215",
        "Div": 0.44
    },
    {
        "Currency": "EUR",
        "TransDate": "20160115",
        "Div": 0.45
    },
    {
        "Currency": "EUR",
        "TransDate": "20151215",
        "Div": 0.46
    },
    {
        "Currency": "EUR",
        "TransDate": "20151116",
        "Div": 0.46
    },
    {
        "Currency": "EUR",
        "TransDate": "20151015",
        "Div": 0.46
    },
    {
        "Currency": "EUR",
        "TransDate": "20150915",
        "Div": 0.46
    },
    {
        "Currency": "EUR",
        "TransDate": "20150817",
        "Div": 0.47
    },
    {
        "Currency": "EUR",
        "TransDate": "20150715",
        "Div": 0.62
    },
    {
        "Currency": "EUR",
        "TransDate": "20150615",
        "Div": 0.62
    },
    {
        "Currency": "EUR",
        "TransDate": "20150515",
        "Div": 0.64
    },
    {
        "Currency": "EUR",
        "TransDate": "20150415",
        "Div": 0.64
    },
    {
        "Currency": "EUR",
        "TransDate": "20150316",
        "Div": 0.64
    },
    {
        "Currency": "EUR",
        "TransDate": "20150216",
        "Div": 0.64
    },
    {
        "Currency": "EUR",
        "TransDate": "20150115",
        "Div": 0.63
    },
    {
        "Currency": "EUR",
        "TransDate": "20141215",
        "Div": 0.62
    },
    {
        "Currency": "EUR",
        "TransDate": "20141117",
        "Div": 0.63
    },
    {
        "Currency": "EUR",
        "TransDate": "20141015",
        "Div": 0.62
    },
    {
        "Currency": "EUR",
        "TransDate": "20140915",
        "Div": 0.63
    },
    {
        "Currency": "EUR",
        "TransDate": "20140818",
        "Div": 0.63
    },
    {
        "Currency": "EUR",
        "TransDate": "20140715",
        "Div": 0.48
    },
    {
        "Currency": "EUR",
        "TransDate": "20140616",
        "Div": 0.48
    },
    {
        "Currency": "EUR",
        "TransDate": "20140515",
        "Div": 0.47
    },
    {
        "Currency": "EUR",
        "TransDate": "20140415",
        "Div": 0.47
    },
    {
        "Currency": "EUR",
        "TransDate": "20140317",
        "Div": 0.47
    },
    {
        "Currency": "EUR",
        "TransDate": "20140217",
        "Div": 0.47
    },
    {
        "Currency": "EUR",
        "TransDate": "20140115",
        "Div": 0.62
    },
    {
        "Currency": "EUR",
        "TransDate": "20131216",
        "Div": 0.61
    },
    {
        "Currency": "EUR",
        "TransDate": "20131115",
        "Div": 0.61
    },
    {
        "Currency": "EUR",
        "TransDate": "20131015",
        "Div": 0.61
    },
    {
        "Currency": "EUR",
        "TransDate": "20130916",
        "Div": 0.6
    },
    {
        "Currency": "EUR",
        "TransDate": "20130816",
        "Div": 0.6
    },
    {
        "Currency": "EUR",
        "TransDate": "20130715",
        "Div": 0.74
    },
    {
        "Currency": "EUR",
        "TransDate": "20130617",
        "Div": 0.75
    },
    {
        "Currency": "EUR",
        "TransDate": "20130515",
        "Div": 0.77
    },
    {
        "Currency": "EUR",
        "TransDate": "20130415",
        "Div": 0.76
    },
    {
        "Currency": "EUR",
        "TransDate": "20130315",
        "Div": 0.76
    },
    {
        "Currency": "EUR",
        "TransDate": "20130215",
        "Div": 0.75
    },
    {
        "Currency": "EUR",
        "TransDate": "20130115",
        "Div": 0.77
    },
    {
        "Currency": "EUR",
        "TransDate": "20121217",
        "Div": 0.77
    },
    {
        "Currency": "EUR",
        "TransDate": "20121115",
        "Div": 0.73
    },
    {
        "Currency": "EUR",
        "TransDate": "20121015",
        "Div": 0.73
    },
    {
        "Currency": "EUR",
        "TransDate": "20120917",
        "Div": 0.73
    },
    {
        "Currency": "EUR",
        "TransDate": "20120816",
        "Div": 0.71
    },
    {
        "Currency": "EUR",
        "TransDate": "20120716",
        "Div": 0.55
    },
    {
        "Currency": "EUR",
        "TransDate": "20120615",
        "Div": 0.54
    },
    {
        "Currency": "EUR",
        "TransDate": "20120515",
        "Div": 0.55
    },
    {
        "Currency": "EUR",
        "TransDate": "20120416",
        "Div": 0.55
    },
    {
        "Currency": "EUR",
        "TransDate": "20120315",
        "Div": 0.57
    },
    {
        "Currency": "EUR",
        "TransDate": "20120215",
        "Div": 0.52
    },
    {
        "Currency": "EUR",
        "TransDate": "20120116",
        "Div": 0.52
    },
    {
        "Currency": "EUR",
        "TransDate": "20111215",
        "Div": 0.51
    },
    {
        "Currency": "EUR",
        "TransDate": "20111115",
        "Div": 0.52
    },
    {
        "Currency": "EUR",
        "TransDate": "20111017",
        "Div": 0.52
    },
    {
        "Currency": "EUR",
        "TransDate": "20110915",
        "Div": 0.52
    },
    {
        "Currency": "EUR",
        "TransDate": "20110816",
        "Div": 0.55
    },
    {
        "Currency": "EUR",
        "TransDate": "20110715",
        "Div": 0.58
    },
    {
        "Currency": "EUR",
        "TransDate": "20110615",
        "Div": 0.59
    },
    {
        "Currency": "EUR",
        "TransDate": "20110516",
        "Div": 0.6
    },
    {
        "Currency": "EUR",
        "TransDate": "20110415",
        "Div": 0.6
    },
    {
        "Currency": "EUR",
        "TransDate": "20110315",
        "Div": 0.59
    },
    {
        "Currency": "EUR",
        "TransDate": "20110215",
        "Div": 0.59
    },
    {
        "Currency": "EUR",
        "TransDate": "20110117",
        "Div": 0.88
    },
    {
        "Currency": "EUR",
        "TransDate": "20101215",
        "Div": 0.87
    },
    {
        "Currency": "EUR",
        "TransDate": "20101115",
        "Div": 0.89
    },
    {
        "Currency": "EUR",
        "TransDate": "20101015",
        "Div": 0.9
    },
    {
        "Currency": "EUR",
        "TransDate": "20100915",
        "Div": 0.89
    },
    {
        "Currency": "EUR",
        "TransDate": "20100816",
        "Div": 0.87
    },
    {
        "Currency": "EUR",
        "TransDate": "20100715",
        "Div": 0.78
    },
    {
        "Currency": "EUR",
        "TransDate": "20100615",
        "Div": 0.76
    },
    {
        "Currency": "EUR",
        "TransDate": "20100517",
        "Div": 0.78
    }
]