[
    {
        "Currency": "EUR",
        "TransDate": "20010331",
        "Div": 0.0258401
    },
    {
        "Currency": "EUR",
        "TransDate": "20000331",
        "Div": 0.0156231
    },
    {
        "Currency": "EUR",
        "TransDate": "19990331",
        "Div": 0.038395
    },
    {
        "Currency": "EUR",
        "TransDate": "19980331",
        "Div": 0.016399
    },
    {
        "Currency": "EUR",
        "TransDate": "19970331",
        "Div": 0.03116
    },
    {
        "Currency": "EUR",
        "TransDate": "19960131",
        "Div": 0.0200628
    },
    {
        "Currency": "EUR",
        "TransDate": "19950131",
        "Div": 0.0151562
    },
    {
        "Currency": "EUR",
        "TransDate": "19940331",
        "Div": 0.0227232
    },
    {
        "Currency": "EUR",
        "TransDate": "19930430",
        "Div": 0.0245012
    },
    {
        "Currency": "EUR",
        "TransDate": "19920430",
        "Div": 0.0487112
    },
    {
        "Currency": "EUR",
        "TransDate": "19910331",
        "Div": 0.0596259
    },
    {
        "Currency": "EUR",
        "TransDate": "19900331",
        "Div": 0.0477492
    },
    {
        "Currency": "EUR",
        "TransDate": "19890331",
        "Div": 0.0673685
    },
    {
        "Currency": "EUR",
        "TransDate": "19880331",
        "Div": 0.0335876
    },
    {
        "Currency": "EUR",
        "TransDate": "19870331",
        "Div": 0.0235791
    },
    {
        "Currency": "EUR",
        "TransDate": "19860331",
        "Div": 0.0126643
    },
    {
        "Currency": "EUR",
        "TransDate": "19850331",
        "Div": 0.02955
    },
    {
        "Currency": "EUR",
        "TransDate": "19840331",
        "Div": 0.0258925
    }
]