{
    "Area": "B",
    "FundId": "012004",
    "StarRatingFromEst": 2,
    "Name": "宏利環球基金－土耳其股票基金AA股",
    "NameEng": "Manulife GF Turkey Equity AA",
    "NameWarning": "",
    "CPId": "44",
    "CPName": "宏利資產管理(香港)有限公司",
    "CPNameEng": "Manulife Global Fund",
    "AgentCPId": "42",
    "AgentCPName": "宏利證券投資信託股份有限公司",
    "AgentCPNameEng": "Manulife Asset Management(Taiwan) Co Ltd",
    "RctName": "盧森堡",
    "Count": 197,
    "CurrencyCode": "USD",
    "InceptionYmdOn": "20071119",
    "CategoryId": "438",
    "CategoryName": "土耳其股票",
    "BroadAssetClassId": null,
    "BroadAssetClassName": "股票基金",
    "InvestmentStrategy": "本基金旨在為持有長期投資觀點,為了達至長期回報而願意承擔其投資價值相當大的波幅的風險的投資者提供長期資本增長.",
    "Custodian": "花旗銀行歐洲(盧森堡)",
    "CustodianFee": 0.4,
    "CustodianFeeUnitNameEng": "Percentage",
    "ManagementFee": 1.75,
    "ManagementFeeUnitNameEng": "Percentage",
    "MinInvestment": 20000,
    "MinInvestmentUnit": "Monetary",
    "DistnbutionStatus": "分配",
    "FrontLoadFee": 3,
    "FrontLoadFeeUnitNameEng": "Percentage",
    "SizeTransDate": "20160930",
    "FundSize": 33089386,
    "PriceTransDate": "20161130",
    "Price": 0.548,
    "PerformanceTransDate": "20161031",
    "UpDown": -0.0027,
    "UpDownRate": -0.49,
    "Rr1w": -2.55189,
    "Rr1M": -1.00723,
    "Rr3M": 0.66588,
    "Rr6M": -16.56874,
    "RrThisYear": -0.48654,
    "Rr1Y": -7.85632,
    "Rr2Y": -31.69941,
    "Rr3Y": -34.92571,
    "Rr5Y": -17.56538,
    "Rr10Y": null,
    "RrFromEst": -33.31882,
    "RatingTransDate": "201610",
    "Alpha1Y": -1.47,
    "Beta1Y": 0.86,
    "Sharpe1Y": -0.32,
    "StdDev1Y": 17.7,
    "Alpha3Y": -2.92,
    "Beta3Y": 0.96,
    "Sharpe3Y": -0.16,
    "StdDev3Y": 25.16,
    "AriMean3Y": -0.335,
    "Alpha5Y": -2.6,
    "Beta5Y": 0.96,
    "Sharpe5Y": 0.16,
    "StdDev5Y": 25.35,
    "Alpha10Y": null,
    "Beta10Y": null,
    "Sharpe10Y": null,
    "StdDev10Y": null,
    "RiskRatingFromEst": 5,
    "ProviderId": "38",
    "EcAllot": "Y",
    "RspAllot": "Y",
    "EcRedem": "Y",
    "EcSwitch": "N",
    "StopTradeType": null,
    "AssertAllocation": [
        {
            "TransDate": "20160601",
            "Name": "股票",
            "InvRate": 0.9752904,
            "SInvRate": 97.52904,
            "LInvRate": 97.52904
        },
        {
            "TransDate": "20160601",
            "Name": "其他",
            "InvRate": 0.0247096,
            "SInvRate": 2.47096,
            "LInvRate": 2.47096
        }
    ],
    "Recent30DPrice": [
        {
            "TransDate": "20161130",
            "Price": 0.548
        },
        {
            "TransDate": "20161129",
            "Price": 0.5507
        },
        {
            "TransDate": "20161128",
            "Price": 0.5547
        },
        {
            "TransDate": "20161125",
            "Price": 0.5455
        },
        {
            "TransDate": "20161124",
            "Price": 0.5487
        },
        {
            "TransDate": "20161123",
            "Price": 0.5592
        },
        {
            "TransDate": "20161122",
            "Price": 0.5674
        },
        {
            "TransDate": "20161121",
            "Price": 0.568
        },
        {
            "TransDate": "20161118",
            "Price": 0.5684
        },
        {
            "TransDate": "20161117",
            "Price": 0.5677
        },
        {
            "TransDate": "20161116",
            "Price": 0.5697
        },
        {
            "TransDate": "20161115",
            "Price": 0.5789
        },
        {
            "TransDate": "20161114",
            "Price": 0.5738
        },
        {
            "TransDate": "20161111",
            "Price": 0.5841
        },
        {
            "TransDate": "20161110",
            "Price": 0.5931
        },
        {
            "TransDate": "20161109",
            "Price": 0.5982
        },
        {
            "TransDate": "20161108",
            "Price": 0.609
        },
        {
            "TransDate": "20161107",
            "Price": 0.6029
        },
        {
            "TransDate": "20161104",
            "Price": 0.5927
        },
        {
            "TransDate": "20161103",
            "Price": 0.6218
        },
        {
            "TransDate": "20161102",
            "Price": 0.6241
        },
        {
            "TransDate": "20161031",
            "Price": 0.6388
        },
        {
            "TransDate": "20161028",
            "Price": 0.6404
        },
        {
            "TransDate": "20161027",
            "Price": 0.6449
        },
        {
            "TransDate": "20161026",
            "Price": 0.6509
        },
        {
            "TransDate": "20161025",
            "Price": 0.6528
        },
        {
            "TransDate": "20161024",
            "Price": 0.6601
        },
        {
            "TransDate": "20161021",
            "Price": 0.6477
        },
        {
            "TransDate": "20161020",
            "Price": 0.6597
        },
        {
            "TransDate": "20161019",
            "Price": 0.6524
        }
    ],
    "IndustryRatio": [
        {
            "TransDate": "20160601",
            "Name": "Banks",
            "InvRate": 43.31416
        },
        {
            "TransDate": "20160601",
            "Name": "Autos",
            "InvRate": 7.79533
        },
        {
            "TransDate": "20160601",
            "Name": "REITs",
            "InvRate": 7.69004
        },
        {
            "TransDate": "20160601",
            "Name": "Retail - Defensive",
            "InvRate": 7.39271
        },
        {
            "TransDate": "20160601",
            "Name": "Engineering & Construction",
            "InvRate": 6.65034
        },
        {
            "TransDate": "20160601",
            "Name": "Oil & Gas - Refining & Marketing",
            "InvRate": 6.64825
        },
        {
            "TransDate": "20160601",
            "Name": "Conglomerates",
            "InvRate": 4.72609
        },
        {
            "TransDate": "20160601",
            "Name": "Communication Services",
            "InvRate": 3.40432
        },
        {
            "TransDate": "20160601",
            "Name": "Beverages - Non-Alcoholic",
            "InvRate": 3.35393
        },
        {
            "TransDate": "20160601",
            "Name": "Farm & Construction Machinery",
            "InvRate": 2.90537
        },
        {
            "TransDate": "20160601",
            "Name": "Building Materials",
            "InvRate": 1.88812
        },
        {
            "TransDate": "20160601",
            "Name": "Aerospace & Defense",
            "InvRate": 1.03407
        },
        {
            "TransDate": "20160601",
            "Name": "Industrial Products",
            "InvRate": 0.72631
        }
    ]
}