{
    "Area": "B",
    "FundId": "042133",
    "StarRatingFromEst": null,
    "Name": "貝萊德美元儲備基金 A2 美元",
    "NameEng": "BGF US Dollar Reserve A2 USD",
    "NameWarning": "",
    "CPId": "33",
    "CPName": "貝萊德(盧森堡)公司",
    "CPNameEng": "BlackRock (Luxembourg) SA",
    "AgentCPId": "101",
    "AgentCPName": "貝萊德證券投資信託股份有限公司",
    "AgentCPNameEng": "BlackRock Investment Mngt (Taiwan) Ltd",
    "RctName": "盧森堡",
    "Count": 46,
    "CurrencyCode": "USD",
    "InceptionYmdOn": "19931130",
    "CategoryId": "771",
    "CategoryName": "貨幣市場 - 美元（短期）",
    "BroadAssetClassId": null,
    "BroadAssetClassName": "貨幣市場",
    "InvestmentStrategy": "美林貨幣基金爭取增值,同時兼顧保本及維持高度套現能力.基金將不少於90%總資產淨值投資以美元定價的投資級定息可轉讓證券及美元現金.基金的管理方式維持資產平均剩餘投資期不超過12個月.",
    "Custodian": "紐約梅隆銀行(國際)有限公司",
    "CustodianFee": 0.441,
    "CustodianFeeUnitNameEng": "Percentage",
    "ManagementFee": 0.45,
    "ManagementFeeUnitNameEng": "Percentage",
    "MinInvestment": 5000,
    "MinInvestmentUnit": "Monetary",
    "DistnbutionStatus": "不分配",
    "FrontLoadFee": 0.5,
    "FrontLoadFeeUnitNameEng": "Percentage",
    "SizeTransDate": "20160930",
    "FundSize": 600388884,
    "PriceTransDate": "20161130",
    "Price": 151.07,
    "PerformanceTransDate": "20161031",
    "UpDown": 0,
    "UpDownRate": 0,
    "Rr1w": 0.01325,
    "Rr1M": 0.03312,
    "Rr3M": 0.07952,
    "Rr6M": 0.09942,
    "RrThisYear": 0.13925,
    "Rr1Y": 0.12597,
    "Rr2Y": 0.1326,
    "Rr3Y": 0.17245,
    "Rr5Y": 0.12596,
    "Rr10Y": 1.84789,
    "RrFromEst": 61.69164,
    "RatingTransDate": null,
    "Alpha1Y": -0.39,
    "Beta1Y": 1.8,
    "Sharpe1Y": -4.52,
    "StdDev1Y": 0.04,
    "Alpha3Y": 0.11,
    "Beta3Y": -0.65,
    "Sharpe3Y": -1.43,
    "StdDev3Y": 0.04,
    "AriMean3Y": 0.005,
    "Alpha5Y": -0.08,
    "Beta5Y": 0.03,
    "Sharpe5Y": -1.88,
    "StdDev5Y": 0.04,
    "Alpha10Y": -0.1,
    "Beta10Y": -1.19,
    "Sharpe10Y": -0.58,
    "StdDev10Y": 1.08,
    "RiskRatingFromEst": 1,
    "ProviderId": "94",
    "EcAllot": "Y",
    "RspAllot": "Y",
    "EcRedem": "Y",
    "EcSwitch": "Y",
    "StopTradeType": null,
    "AssertAllocation": [
        {
            "TransDate": "20161001",
            "Name": "現金",
            "InvRate": 0.9187736,
            "SInvRate": 91.87736,
            "LInvRate": 91.87736
        },
        {
            "TransDate": "20161001",
            "Name": "其他",
            "InvRate": 0.0812264,
            "SInvRate": 8.12264,
            "LInvRate": 8.12264
        }
    ],
    "Recent30DPrice": [
        {
            "TransDate": "20161130",
            "Price": 151.07
        },
        {
            "TransDate": "20161129",
            "Price": 151.07
        },
        {
            "TransDate": "20161128",
            "Price": 151.07
        },
        {
            "TransDate": "20161125",
            "Price": 151.06
        },
        {
            "TransDate": "20161124",
            "Price": 151.06
        },
        {
            "TransDate": "20161123",
            "Price": 151.06
        },
        {
            "TransDate": "20161122",
            "Price": 151.06
        },
        {
            "TransDate": "20161121",
            "Price": 151.05
        },
        {
            "TransDate": "20161118",
            "Price": 151.05
        },
        {
            "TransDate": "20161117",
            "Price": 151.05
        },
        {
            "TransDate": "20161116",
            "Price": 151.05
        },
        {
            "TransDate": "20161115",
            "Price": 151.05
        },
        {
            "TransDate": "20161114",
            "Price": 151.04
        },
        {
            "TransDate": "20161111",
            "Price": 151.04
        },
        {
            "TransDate": "20161110",
            "Price": 151.04
        },
        {
            "TransDate": "20161109",
            "Price": 151.04
        },
        {
            "TransDate": "20161108",
            "Price": 151.04
        },
        {
            "TransDate": "20161107",
            "Price": 151.03
        },
        {
            "TransDate": "20161104",
            "Price": 151.03
        },
        {
            "TransDate": "20161103",
            "Price": 151.03
        },
        {
            "TransDate": "20161102",
            "Price": 151.03
        },
        {
            "TransDate": "20161031",
            "Price": 151.02
        },
        {
            "TransDate": "20161028",
            "Price": 151.02
        },
        {
            "TransDate": "20161027",
            "Price": 151.01
        },
        {
            "TransDate": "20161026",
            "Price": 151.01
        },
        {
            "TransDate": "20161025",
            "Price": 151.01
        },
        {
            "TransDate": "20161024",
            "Price": 151
        },
        {
            "TransDate": "20161021",
            "Price": 151
        },
        {
            "TransDate": "20161020",
            "Price": 150.99
        },
        {
            "TransDate": "20161019",
            "Price": 150.99
        }
    ],
    "IndustryRatio": []
}