{
    "Area": "A",
    "FundId": "Man026",
    "StarRatingFromEst": null,
    "Name": "宏利亞澳入息成長平衡基金A不配息（澳幣避險）",
    "NameEng": "Manulife Asia Pac Inc and Gr Bal A AUD",
    "NameWarning": "本基金有相當比例投資於非投資等級之高風險債券",
    "CPId": "42",
    "CPName": "宏利證券投資信託股份有限公司",
    "CPNameEng": "Manulife Asset Management(Taiwan) Co Ltd",
    "AgentCPId": "42",
    "AgentCPName": "宏利證券投資信託股份有限公司",
    "AgentCPNameEng": "Manulife Asset Management(Taiwan) Co Ltd",
    "RctName": "台灣",
    "Count": 12,
    "CurrencyCode": "AUD",
    "InceptionYmdOn": "20141030",
    "CategoryId": "206",
    "CategoryName": "亞洲股債混合",
    "BroadAssetClassId": null,
    "BroadAssetClassName": "股票債券混和基金",
    "InvestmentStrategy": "原則上,本基金自成立日起屆滿三個月後:(1)投資亞澳地區(包括印度,印尼,香港,菲律賓,泰國,韓國,新加坡,澳洲,紐西蘭,馬來西亞,大陸等國家或地區,不含日本)之股票,債券及其他固定收益證券之總額應達基金淨資產價值之百分之七十以上;有關(亞澳地區之股票)係指於亞澳地區證券交易所及亞澳地區經金管會核准之店頭市場交易之股票(含承銷股票);有關(亞澳地區之債券)係指由亞澳地區之國家或機構所保證或發行之債券,由亞澳地區以外之國家或機構所保證或發行而於亞澳地區發行或交易之債券,以亞澳地區國家貨幣計價之債券及依彭博(Bloomberg)資訊系統顯示(涉險國家)為亞澳地區國家之債券.",
    "Custodian": "元大商業銀行",
    "CustodianFee": 0.24,
    "CustodianFeeUnitNameEng": "Percentage",
    "ManagementFee": 1.6,
    "ManagementFeeUnitNameEng": "Percentage",
    "MinInvestment": 1000,
    "MinInvestmentUnit": "Monetary",
    "DistnbutionStatus": "不分配",
    "FrontLoadFee": 3,
    "FrontLoadFeeUnitNameEng": "Percentage",
    "SizeTransDate": "20161031",
    "FundSize": 6597731.93,
    "PriceTransDate": "20161130",
    "Price": 9.5442,
    "PerformanceTransDate": "20161031",
    "UpDown": -0.0075,
    "UpDownRate": -0.08,
    "Rr1w": -1.38952,
    "Rr1M": -1.51057,
    "Rr3M": 0.94516,
    "Rr6M": 7.04811,
    "RrThisYear": 7.60219,
    "Rr1Y": 5.89563,
    "Rr2Y": -2.48991,
    "Rr3Y": null,
    "Rr5Y": null,
    "Rr10Y": null,
    "RrFromEst": -2.91603,
    "RatingTransDate": null,
    "Alpha1Y": null,
    "Beta1Y": null,
    "Sharpe1Y": 0.69,
    "StdDev1Y": 19.77,
    "Alpha3Y": null,
    "Beta3Y": null,
    "Sharpe3Y": null,
    "StdDev3Y": null,
    "AriMean3Y": null,
    "Alpha5Y": null,
    "Beta5Y": null,
    "Sharpe5Y": null,
    "StdDev5Y": null,
    "Alpha10Y": null,
    "Beta10Y": null,
    "Sharpe10Y": null,
    "StdDev10Y": null,
    "RiskRatingFromEst": 4,
    "ProviderId": "38",
    "EcAllot": "Y",
    "RspAllot": "N",
    "EcRedem": "Y",
    "EcSwitch": "Y",
    "StopTradeType": null,
    "AssertAllocation": [
        {
            "TransDate": "20160901",
            "Name": "股票",
            "InvRate": 0.5915579,
            "SInvRate": 59.15579,
            "LInvRate": 59.15579
        },
        {
            "TransDate": "20160901",
            "Name": "債券",
            "InvRate": 0.3436683,
            "SInvRate": 34.36683,
            "LInvRate": 34.36683
        },
        {
            "TransDate": "20160901",
            "Name": "現金",
            "InvRate": 0.0404313,
            "SInvRate": 4.04313,
            "LInvRate": 4.04313
        },
        {
            "TransDate": "20160901",
            "Name": "其他",
            "InvRate": 0.0243425,
            "SInvRate": 2.43425,
            "LInvRate": 2.43425
        }
    ],
    "Recent30DPrice": [
        {
            "TransDate": "20161130",
            "Price": 9.5442
        },
        {
            "TransDate": "20161129",
            "Price": 9.5337
        },
        {
            "TransDate": "20161128",
            "Price": 9.5412
        },
        {
            "TransDate": "20161125",
            "Price": 9.5176
        },
        {
            "TransDate": "20161124",
            "Price": 9.5035
        },
        {
            "TransDate": "20161123",
            "Price": 9.5278
        },
        {
            "TransDate": "20161122",
            "Price": 9.4985
        },
        {
            "TransDate": "20161121",
            "Price": 9.4373
        },
        {
            "TransDate": "20161118",
            "Price": 9.4536
        },
        {
            "TransDate": "20161117",
            "Price": 9.4603
        },
        {
            "TransDate": "20161116",
            "Price": 9.4445
        },
        {
            "TransDate": "20161115",
            "Price": 9.4356
        },
        {
            "TransDate": "20161114",
            "Price": 9.4283
        },
        {
            "TransDate": "20161111",
            "Price": 9.525
        },
        {
            "TransDate": "20161110",
            "Price": 9.6642
        },
        {
            "TransDate": "20161109",
            "Price": 9.5783
        },
        {
            "TransDate": "20161108",
            "Price": 9.6958
        },
        {
            "TransDate": "20161107",
            "Price": 9.6613
        },
        {
            "TransDate": "20161104",
            "Price": 9.5919
        },
        {
            "TransDate": "20161103",
            "Price": 9.6115
        },
        {
            "TransDate": "20161102",
            "Price": 9.6521
        },
        {
            "TransDate": "20161101",
            "Price": 9.7313
        },
        {
            "TransDate": "20161031",
            "Price": 9.7083
        },
        {
            "TransDate": "20161028",
            "Price": 9.7165
        },
        {
            "TransDate": "20161027",
            "Price": 9.7499
        },
        {
            "TransDate": "20161026",
            "Price": 9.7821
        },
        {
            "TransDate": "20161025",
            "Price": 9.8437
        },
        {
            "TransDate": "20161024",
            "Price": 9.8451
        },
        {
            "TransDate": "20161020",
            "Price": 9.8374
        },
        {
            "TransDate": "20161019",
            "Price": 9.8271
        }
    ],
    "IndustryRatio": [
        {
            "TransDate": "20160901",
            "Name": "Banks",
            "InvRate": 10.85675
        },
        {
            "TransDate": "20160901",
            "Name": "Computer Hardware",
            "InvRate": 6.28571
        },
        {
            "TransDate": "20160901",
            "Name": "Communication Services",
            "InvRate": 5.86249
        },
        {
            "TransDate": "20160901",
            "Name": "Brokers & Exchanges",
            "InvRate": 3.74355
        },
        {
            "TransDate": "20160901",
            "Name": "Semiconductors",
            "InvRate": 3.37235
        },
        {
            "TransDate": "20160901",
            "Name": "REITs",
            "InvRate": 3.32144
        },
        {
            "TransDate": "20160901",
            "Name": "Insurance - Life",
            "InvRate": 3.22513
        },
        {
            "TransDate": "20160901",
            "Name": "Online Media",
            "InvRate": 2.65339
        },
        {
            "TransDate": "20160901",
            "Name": "Travel & Leisure",
            "InvRate": 2.38373
        },
        {
            "TransDate": "20160901",
            "Name": "Transportation & Logistics",
            "InvRate": 2.01153
        },
        {
            "TransDate": "20160901",
            "Name": "Autos",
            "InvRate": 1.89717
        },
        {
            "TransDate": "20160901",
            "Name": "Homebuilding & Construction",
            "InvRate": 1.749
        },
        {
            "TransDate": "20160901",
            "Name": "Industrial Products",
            "InvRate": 1.69278
        },
        {
            "TransDate": "20160901",
            "Name": "Chemicals",
            "InvRate": 1.14334
        },
        {
            "TransDate": "20160901",
            "Name": "Real Estate",
            "InvRate": 1.07793
        },
        {
            "TransDate": "20160901",
            "Name": "Utilities - Regulated",
            "InvRate": 1.05826
        },
        {
            "TransDate": "20160901",
            "Name": "Conglomerates",
            "InvRate": 1.00523
        },
        {
            "TransDate": "20160901",
            "Name": "Beverages - Alcoholic",
            "InvRate": 0.81037
        },
        {
            "TransDate": "20160901",
            "Name": "Metals & Mining",
            "InvRate": 0.80179
        },
        {
            "TransDate": "20160901",
            "Name": "Health Care Providers",
            "InvRate": 0.68945
        },
        {
            "TransDate": "20160901",
            "Name": "Insurance - Property & Casualty",
            "InvRate": 0.68295
        },
        {
            "TransDate": "20160901",
            "Name": "Asset Management",
            "InvRate": 0.67398
        },
        {
            "TransDate": "20160901",
            "Name": "Retail - Apparel & Specialty",
            "InvRate": 0.56244
        },
        {
            "TransDate": "20160901",
            "Name": "Application Software",
            "InvRate": 0.48031
        },
        {
            "TransDate": "20160901",
            "Name": "Drug Manufacturers",
            "InvRate": 0.2818
        },
        {
            "TransDate": "20160901",
            "Name": "Oil & Gas - Refining & Marketing",
            "InvRate": 0.19276
        },
        {
            "TransDate": "20160901",
            "Name": "Consumer Packaged Goods",
            "InvRate": 0.15154
        },
        {
            "TransDate": "20160901",
            "Name": "Tobacco Products",
            "InvRate": 0.1005
        },
        {
            "TransDate": "20160901",
            "Name": "Credit Services",
            "InvRate": 0.06402
        },
        {
            "TransDate": "20160901",
            "Name": "Building Materials",
            "InvRate": 0.06184
        },
        {
            "TransDate": "20160901",
            "Name": "Engineering & Construction",
            "InvRate": 0.05594
        },
        {
            "TransDate": "20160901",
            "Name": "Utilities - Independent Power Producers",
            "InvRate": 0.04037
        },
        {
            "TransDate": "20160901",
            "Name": "Entertainment",
            "InvRate": 0.03882
        },
        {
            "TransDate": "20160901",
            "Name": "Oil & Gas - Integrated",
            "InvRate": 0.03814
        },
        {
            "TransDate": "20160901",
            "Name": "Steel",
            "InvRate": 0.03191
        },
        {
            "TransDate": "20160901",
            "Name": "Agriculture",
            "InvRate": 0.02946
        },
        {
            "TransDate": "20160901",
            "Name": "Coal",
            "InvRate": 0.02759
        }
    ]
}